ixpeobssim/__init__.py
ixpeobssim/__version__.py
ixpeobssim/benchmarks/__init__.py
ixpeobssim/benchmarks/gray_filter.py
ixpeobssim/benchmarks/ixpesim.py
ixpeobssim/benchmarks/stokes_errors.py
ixpeobssim/benchmarks/toy_polconst.py
ixpeobssim/benchmarks/toy_pollin.py
ixpeobssim/benchmarks/summary/toy_polconst_summary.fits
ixpeobssim/benchmarks/summary/toy_pollin_summary.fits
ixpeobssim/bin/__init__.py
ixpeobssim/bin/xpancrkey.py
ixpeobssim/bin/xpbin.py
ixpeobssim/bin/xpbinview.py
ixpeobssim/bin/xpcalib.py
ixpeobssim/bin/xpchrgmap.py
ixpeobssim/bin/xpevtdisplay.py
ixpeobssim/bin/xpevtstat.py
ixpeobssim/bin/xpexposure.py
ixpeobssim/bin/xpgrppha.py
ixpeobssim/bin/xpirfview.py
ixpeobssim/bin/xpmdp.py
ixpeobssim/bin/xpobsdisplay.py
ixpeobssim/bin/xpobssim.py
ixpeobssim/bin/xpobsview.py
ixpeobssim/bin/xpophase.py
ixpeobssim/bin/xpphase.py
ixpeobssim/bin/xpphotonlist.py
ixpeobssim/bin/xppicorr.py
ixpeobssim/bin/xppimms.py
ixpeobssim/bin/xpradialprofile.py
ixpeobssim/bin/xpselect.py
ixpeobssim/bin/xpsimfmt.py
ixpeobssim/bin/xpsimspec.py
ixpeobssim/bin/xpsonify.py
ixpeobssim/bin/xpsrccoords.py
ixpeobssim/bin/xpstokesalign.py
ixpeobssim/bin/xpstokesrandom.py
ixpeobssim/bin/xpstokesshuffle.py
ixpeobssim/bin/xpstokessmear.py
ixpeobssim/bin/xpstripmc.py
ixpeobssim/bin/xpvisibility.py
ixpeobssim/bin/xpxspec.py
ixpeobssim/binning/__init__.py
ixpeobssim/binning/base.py
ixpeobssim/binning/detector.py
ixpeobssim/binning/exposure.py
ixpeobssim/binning/fmt.py
ixpeobssim/binning/misc.py
ixpeobssim/binning/polarization.py
ixpeobssim/caldb/ixpe/gpd/bcf/chrgparams/ixpe_vanilla_d1_chrgparams.fits
ixpeobssim/caldb/ixpe/gpd/bcf/chrgparams/ixpe_vanilla_d2_chrgparams.fits
ixpeobssim/caldb/ixpe/gpd/bcf/chrgparams/ixpe_vanilla_d3_chrgparams.fits
ixpeobssim/caldb/ixpe/gpd/cpf/arf/ixpe_d1_obssim20211209_alpha075_gray_v013.arf
ixpeobssim/caldb/ixpe/gpd/cpf/arf/ixpe_d1_obssim20211209_alpha075_v013.arf
ixpeobssim/caldb/ixpe/gpd/cpf/arf/ixpe_d1_obssim20211209_alpha075simple_gray_v013.arf
ixpeobssim-31.1.1.dist-info/licenses/LICENSE
ixpeobssim-31.1.1.dist-info/METADATA
ixpeobssim-31.1.1.dist-info/WHEEL
ixpeobssim-31.1.1.dist-info/entry_points.txt
ixpeobssim-31.1.1.dist-info/top_level.txt
ixpeobssim-31.1.1.dist-info/RECORD
